{
  "generated_at": "2026-07-13T22:39:41+08:00",
  "accounts": [
    {
      "handle": "TrendForce",
      "platform": "X",
      "is_own": true,
      "post_count": 575,
      "last_post_at": "2026-07-13T22:01:29+08:00",
      "days_since_last_post": 0,
      "status": "active"
    },
    {
      "handle": "technews_tw",
      "platform": "X",
      "is_own": true,
      "post_count": 1422,
      "last_post_at": "2026-07-13T22:01:56+08:00",
      "days_since_last_post": 0,
      "status": "active"
    },
    {
      "handle": "dylan522p",
      "platform": "X",
      "is_own": false,
      "post_count": 596,
      "last_post_at": "2026-07-12T15:03:10+08:00",
      "days_since_last_post": 1,
      "status": "active"
    },
    {
      "handle": "SemiAnalysis_",
      "platform": "X",
      "is_own": false,
      "post_count": 818,
      "last_post_at": "2026-07-13T01:00:23+08:00",
      "days_since_last_post": 0,
      "status": "active"
    },
    {
      "handle": "jukan05",
      "platform": "X",
      "is_own": false,
      "post_count": 606,
      "last_post_at": "2026-07-13T21:30:46+08:00",
      "days_since_last_post": 0,
      "status": "active"
    },
    {
      "handle": "QQ_Timmy",
      "platform": "X",
      "is_own": false,
      "post_count": 453,
      "last_post_at": "2026-07-13T22:39:41+08:00",
      "days_since_last_post": 0,
      "status": "active"
    },
    {
      "handle": "tphuang",
      "platform": "X",
      "is_own": false,
      "post_count": 265,
      "last_post_at": "2026-07-13T20:40:46+08:00",
      "days_since_last_post": 0,
      "status": "active"
    },
    {
      "handle": "tengyanAI",
      "platform": "X",
      "is_own": false,
      "post_count": 390,
      "last_post_at": "2026-07-13T22:39:08+08:00",
      "days_since_last_post": 0,
      "status": "active"
    },
    {
      "handle": "TrendForce.tw",
      "platform": "Facebook",
      "is_own": true,
      "post_count": 531,
      "last_post_at": "2026-07-09T10:00:00+00:00",
      "days_since_last_post": 4,
      "status": "stale"
    },
    {
      "handle": "technewsinside",
      "platform": "Facebook",
      "is_own": true,
      "post_count": 1213,
      "last_post_at": "2026-07-13T08:40:00+00:00",
      "days_since_last_post": 0,
      "status": "active"
    },
    {
      "handle": "ctee.fans",
      "platform": "Facebook",
      "is_own": false,
      "post_count": 1189,
      "last_post_at": "2026-07-13T14:12:37.573842+00:00",
      "days_since_last_post": 0,
      "status": "active"
    },
    {
      "handle": "yutinghaosfinance",
      "platform": "Facebook",
      "is_own": false,
      "post_count": 989,
      "last_post_at": "2026-07-13T10:09:00+00:00",
      "days_since_last_post": 0,
      "status": "active"
    }
  ]
}