{
  "generated_at": "2026-07-18T00:36:25.479085+00:00",
  "date": "2026-07-18",
  "summaries": [
    {
      "category": "topic_gap",
      "ref": {
        "cluster_id": 13,
        "label": "hynix / sk / samsung / memory"
      },
      "text": "「hynix / sk / samsung / memory」議題出現內容缺口。對手SemiAnalysis_、jukan05、QQ_Timmy等已發布89篇, 互動量達59,482。我方僅15篇覆蓋。建議優先規劃選題切入, 縮小報導落差。",
      "char_count": 120,
      "id": "topic_gap-0"
    },
    {
      "category": "rising_topic",
      "ref": {
        "platform": "X",
        "topic_id": 3,
        "label": "tsmc / intel / packaging / foundry"
      },
      "text": "X平台「tsmc / intel / packaging / foundry」議題升溫, 熱度評分74.6。領先帳號為technews_tw, 建議關注後續擴散。",
      "char_count": 81,
      "id": "rising_topic-1"
    },
    {
      "category": "rising_topic",
      "ref": {
        "platform": "X",
        "topic_id": 14,
        "label": "ai / trendforce / pcb / physical"
      },
      "text": "X平台「ai / trendforce / pcb / physical」議題升溫, 熱度評分64.5。領先帳號為SemiAnalysis_, 建議關注後續擴散。",
      "char_count": 81,
      "id": "rising_topic-2"
    },
    {
      "category": "rising_topic",
      "ref": {
        "platform": "X",
        "topic_id": 0,
        "label": "ai / 台積電 / trendforce / memory"
      },
      "text": "X平台「ai / 台積電 / trendforce / memory」議題升溫, 熱度評分60.3。近7日volume +9% vs prior 7d, engagement rate -2%, 8 account(s) posting。",
      "char_count": 119,
      "id": "rising_topic-3"
    },
    {
      "category": "rising_topic",
      "ref": {
        "platform": "Facebook",
        "topic_id": 13,
        "label": "hynix / sk / samsung / memory"
      },
      "text": "Facebook平台「hynix / sk / samsung / memory」議題升溫, 熱度評分58.6。領先帳號為ctee.fans, 建議關注後續擴散。",
      "char_count": 81,
      "id": "rising_topic-4"
    },
    {
      "category": "rising_topic",
      "ref": {
        "platform": "Facebook",
        "topic_id": 8,
        "label": "spacex / ipo / 馬斯克 / starlink"
      },
      "text": "Facebook平台「spacex / ipo / 馬斯克 / starlink」議題升溫, 熱度評分58.4。領先帳號為technewsinside, 建議關注後續擴散。",
      "char_count": 86,
      "id": "rising_topic-5"
    },
    {
      "category": "sentiment",
      "ref": {
        "total_posts": 254
      },
      "text": "過去24小時共監測254篇貼文, 正面33.1%、中立39.0%、負面28.0%。正面聲量較前一時段上升80.0個百分點。最高熱度議題為「ai / google / gpu / kimi」, 熱度評分90.0。",
      "char_count": 105,
      "id": "sentiment-6"
    },
    {
      "category": "engagement",
      "ref": {
        "topic_id": 1,
        "label": "ai / google / gpu / kimi"
      },
      "text": "互動最高議題為「ai / google / gpu / kimi」。累計互動16,141, 發文203篇。建議延伸相關報導, 承接既有討論熱度。建議持續追蹤後續發展, 適時調整報導與互動策略。",
      "char_count": 96,
      "id": "engagement-7"
    },
    {
      "category": "engagement",
      "ref": {
        "topic_id": 13,
        "label": "台積大擴廠 / 早晨財經速解讀 / 利多卻重挫 / 資金輪動還是泡沫破滅"
      },
      "text": "互動最高議題為「台積大擴廠 / 早晨財經速解讀 / 利多卻重挫 / 資金輪動還是泡沫破滅」。累計互動906, 發文2篇。建議延伸相關報導, 承接既有討論熱度。建議納入每日監測重點, 觀察後續數據變化。",
      "char_count": 100,
      "id": "engagement-8"
    },
    {
      "category": "engagement",
      "ref": {
        "topic_id": 4,
        "label": "紐約州首開全美先例 / 讓州政府有時間制定更完整的管理規範 / 暫停期間不只停止受理新案 / 降低資料中心大量用電對電網造成的壓力"
      },
      "text": "互動最高議題為「紐約州首開全美先例 / 讓州政府有時間制定更完整的管理規範 / 暫停期間不只停止受理新案 / 降低資料中心大量用電對電網造成的壓力」。累計互動565, 發文3篇。建議延伸相關報導, 承接既有討論熱度。",
      "char_count": 108,
      "id": "engagement-9"
    }
  ]
}