{
  "generated_at": "2026-07-18T23:04:58+08:00",
  "time_range": "4h",
  "window": {
    "start_utc": "2026-07-18T19:04:58+08:00",
    "end_utc": "2026-07-18T23:04:58+08:00",
    "start_tw": "Jul 18, 19:04",
    "end_tw": "Jul 18, 23:04"
  },
  "keyword": null,
  "widgets": {
    "sentiment_overview": {
      "total_posts": 15,
      "sentiment_counts": {
        "negative": 5,
        "positive": 5,
        "neutral": 5
      },
      "sentiment_share": {
        "negative": 0.333,
        "positive": 0.333,
        "neutral": 0.333
      },
      "top_terms": [
        "半導",
        "導體",
        "半導體",
        "新突",
        "突破",
        "新突破",
        "團隊",
        "kimi",
        "kimik",
        "moonshot"
      ]
    },
    "temperature_bar": [
      {
        "topic_id": 1,
        "label": "半導體 / 大黑磚 / 筆電充電 / 氮化鎵技術如何改變筆電充電生態",
        "heat": 90.0,
        "volume": 10,
        "engagement": 61,
        "entities": [
          "英特爾",
          "大黑",
          "台灣",
          "美國",
          "日本"
        ]
      },
      {
        "topic_id": 2,
        "label": "ai",
        "heat": 15.1,
        "volume": 3,
        "engagement": 7,
        "entities": [
          "AI",
          "Topoint"
        ]
      },
      {
        "topic_id": 0,
        "label": "kimi / 跑分逼近美國兩大模型 / kimik / 月之暗面",
        "heat": 10.0,
        "volume": 2,
        "engagement": 2,
        "entities": [
          "美國",
          "中國"
        ]
      }
    ],
    "named_entities": [
      {
        "entity": "美國",
        "count": 9
      },
      {
        "entity": "英特爾",
        "count": 5
      },
      {
        "entity": "中國",
        "count": 5
      },
      {
        "entity": "大黑",
        "count": 5
      },
      {
        "entity": "台灣",
        "count": 4
      },
      {
        "entity": "日本",
        "count": 3
      },
      {
        "entity": "China",
        "count": 2
      },
      {
        "entity": "AI",
        "count": 2
      },
      {
        "entity": "日本央行",
        "count": 2
      },
      {
        "entity": "NMPA",
        "count": 1
      },
      {
        "entity": "BCI",
        "count": 1
      },
      {
        "entity": "china",
        "count": 1
      },
      {
        "entity": "Topoint",
        "count": 1
      },
      {
        "entity": "聯準會",
        "count": 1
      },
      {
        "entity": "富邦",
        "count": 1
      }
    ],
    "sentiment_trend_curve": [
      {
        "bucket_start": "2026-07-18T19:04:57.999994+08:00",
        "bucket_end": "2026-07-18T19:22:06.571423+08:00",
        "positive": 0,
        "neutral": 0,
        "negative": 0
      },
      {
        "bucket_start": "2026-07-18T19:22:06.571423+08:00",
        "bucket_end": "2026-07-18T19:39:15.142852+08:00",
        "positive": 1,
        "neutral": 1,
        "negative": 1
      },
      {
        "bucket_start": "2026-07-18T19:39:15.142852+08:00",
        "bucket_end": "2026-07-18T19:56:23.714281+08:00",
        "positive": 1,
        "neutral": 0,
        "negative": 0
      },
      {
        "bucket_start": "2026-07-18T19:56:23.714281+08:00",
        "bucket_end": "2026-07-18T20:13:32.285710+08:00",
        "positive": 0,
        "neutral": 2,
        "negative": 1
      },
      {
        "bucket_start": "2026-07-18T20:13:32.285710+08:00",
        "bucket_end": "2026-07-18T20:30:40.857139+08:00",
        "positive": 0,
        "neutral": 0,
        "negative": 0
      },
      {
        "bucket_start": "2026-07-18T20:30:40.857139+08:00",
        "bucket_end": "2026-07-18T20:47:49.428568+08:00",
        "positive": 0,
        "neutral": 0,
        "negative": 1
      },
      {
        "bucket_start": "2026-07-18T20:47:49.428568+08:00",
        "bucket_end": "2026-07-18T21:04:57.999997+08:00",
        "positive": 1,
        "neutral": 2,
        "negative": 1
      },
      {
        "bucket_start": "2026-07-18T21:04:57.999997+08:00",
        "bucket_end": "2026-07-18T21:22:06.571426+08:00",
        "positive": 0,
        "neutral": 0,
        "negative": 0
      },
      {
        "bucket_start": "2026-07-18T21:22:06.571426+08:00",
        "bucket_end": "2026-07-18T21:39:15.142855+08:00",
        "positive": 1,
        "neutral": 0,
        "negative": 0
      },
      {
        "bucket_start": "2026-07-18T21:39:15.142855+08:00",
        "bucket_end": "2026-07-18T21:56:23.714284+08:00",
        "positive": 0,
        "neutral": 0,
        "negative": 0
      },
      {
        "bucket_start": "2026-07-18T21:56:23.714284+08:00",
        "bucket_end": "2026-07-18T22:13:32.285713+08:00",
        "positive": 1,
        "neutral": 0,
        "negative": 0
      },
      {
        "bucket_start": "2026-07-18T22:13:32.285713+08:00",
        "bucket_end": "2026-07-18T22:30:40.857142+08:00",
        "positive": 0,
        "neutral": 0,
        "negative": 0
      },
      {
        "bucket_start": "2026-07-18T22:30:40.857142+08:00",
        "bucket_end": "2026-07-18T22:47:49.428571+08:00",
        "positive": 0,
        "neutral": 0,
        "negative": 0
      },
      {
        "bucket_start": "2026-07-18T22:47:49.428571+08:00",
        "bucket_end": "2026-07-18T23:04:58+08:00",
        "positive": 0,
        "neutral": 0,
        "negative": 0
      }
    ],
    "coverage_focus_ranking": [
      {
        "handle": "tphuang",
        "top_topic_id": 1,
        "top_topic_label": "半導體 / 大黑磚 / 筆電充電 / 氮化鎵技術如何改變筆電充電生態",
        "focus_share": 1.0,
        "post_count": 1
      },
      {
        "handle": "technewsinside",
        "top_topic_id": 1,
        "top_topic_label": "半導體 / 大黑磚 / 筆電充電 / 氮化鎵技術如何改變筆電充電生態",
        "focus_share": 1.0,
        "post_count": 2
      },
      {
        "handle": "ctee.fans",
        "top_topic_id": 1,
        "top_topic_label": "半導體 / 大黑磚 / 筆電充電 / 氮化鎵技術如何改變筆電充電生態",
        "focus_share": 1.0,
        "post_count": 2
      },
      {
        "handle": "technews_tw",
        "top_topic_id": 1,
        "top_topic_label": "半導體 / 大黑磚 / 筆電充電 / 氮化鎵技術如何改變筆電充電生態",
        "focus_share": 0.5,
        "post_count": 8
      },
      {
        "handle": "tengyanAI",
        "top_topic_id": 1,
        "top_topic_label": "半導體 / 大黑磚 / 筆電充電 / 氮化鎵技術如何改變筆電充電生態",
        "focus_share": 0.5,
        "post_count": 2
      }
    ],
    "top_engagement_ranking": [
      {
        "topic_id": 1,
        "label": "半導體 / 大黑磚 / 筆電充電 / 氮化鎵技術如何改變筆電充電生態",
        "total_engagement": 61,
        "post_count": 10
      },
      {
        "topic_id": 2,
        "label": "ai",
        "total_engagement": 7,
        "post_count": 3
      },
      {
        "topic_id": 0,
        "label": "kimi / 跑分逼近美國兩大模型 / kimik / 月之暗面",
        "total_engagement": 2,
        "post_count": 2
      }
    ],
    "posting_timeslot_analysis": {
      "slots": {
        "morning": {
          "post_count": 0,
          "likes": 0,
          "engagement": 0,
          "avg_engagement": 0.0
        },
        "afternoon": {
          "post_count": 0,
          "likes": 0,
          "engagement": 0,
          "avg_engagement": 0.0
        },
        "evening": {
          "post_count": 0,
          "likes": 0,
          "engagement": 0,
          "avg_engagement": 0.0
        },
        "late_night": {
          "post_count": 0,
          "likes": 0,
          "engagement": 0,
          "avg_engagement": 0.0
        }
      },
      "peak_slot": null
    },
    "competitor_mentions": null,
    "platform_share_bar": null,
    "platform_keyword_ranking": null
  },
  "note": "competitor_mentions/platform_share_bar/platform_keyword_ranking require a keyword argument"
}