{
  "generated_at": "2026-07-24T14:20:00+00:00",
  "time_range": "1h",
  "window": {
    "start_utc": "2026-07-24T13:20:00+00:00",
    "end_utc": "2026-07-24T14:20:00+00:00",
    "start_tw": "Jul 24, 21:20",
    "end_tw": "Jul 24, 22:20"
  },
  "keyword": null,
  "widgets": {
    "sentiment_overview": {
      "total_posts": 9,
      "sentiment_counts": {
        "positive": 5,
        "negative": 3,
        "neutral": 1
      },
      "sentiment_share": {
        "positive": 0.556,
        "negative": 0.333,
        "neutral": 0.111
      },
      "top_terms": [
        "排名",
        "名第",
        "二的",
        "巴西",
        "排名第",
        "名第二",
        "第二的",
        "排名第二",
        "名第二的",
        "逐步"
      ]
    },
    "temperature_bar": [
      {
        "topic_id": 0,
        "label": "全年需求可能寫下 / 逐步轉型為人工智慧與科技產業重鎮 / 紐約正從傳統金融中心 / 若下半年維持相同速度",
        "heat": 50.0,
        "volume": 9,
        "engagement": 890,
        "entities": [
          "美國",
          "巴西",
          "中國",
          "青少年",
          "日本"
        ]
      }
    ],
    "named_entities": [
      {
        "entity": "美國",
        "count": 4
      },
      {
        "entity": "巴西",
        "count": 3
      },
      {
        "entity": "中國",
        "count": 3
      },
      {
        "entity": "青少年",
        "count": 2
      },
      {
        "entity": "日本",
        "count": 2
      },
      {
        "entity": "聊天",
        "count": 1
      },
      {
        "entity": "墨西哥",
        "count": 1
      },
      {
        "entity": "北京政府",
        "count": 1
      },
      {
        "entity": "明文",
        "count": 1
      },
      {
        "entity": "紐約",
        "count": 1
      },
      {
        "entity": "曼哈頓",
        "count": 1
      },
      {
        "entity": "太瓦",
        "count": 1
      },
      {
        "entity": "印度",
        "count": 1
      },
      {
        "entity": "俄羅斯",
        "count": 1
      },
      {
        "entity": "四國",
        "count": 1
      }
    ],
    "sentiment_trend_curve": [
      {
        "bucket_start": "2026-07-24T13:20:00.000002+00:00",
        "bucket_end": "2026-07-24T13:24:17.142859+00:00",
        "positive": 0,
        "neutral": 0,
        "negative": 0
      },
      {
        "bucket_start": "2026-07-24T13:24:17.142859+00:00",
        "bucket_end": "2026-07-24T13:28:34.285716+00:00",
        "positive": 0,
        "neutral": 0,
        "negative": 0
      },
      {
        "bucket_start": "2026-07-24T13:28:34.285716+00:00",
        "bucket_end": "2026-07-24T13:32:51.428573+00:00",
        "positive": 0,
        "neutral": 0,
        "negative": 0
      },
      {
        "bucket_start": "2026-07-24T13:32:51.428573+00:00",
        "bucket_end": "2026-07-24T13:37:08.571430+00:00",
        "positive": 0,
        "neutral": 0,
        "negative": 0
      },
      {
        "bucket_start": "2026-07-24T13:37:08.571430+00:00",
        "bucket_end": "2026-07-24T13:41:25.714287+00:00",
        "positive": 0,
        "neutral": 0,
        "negative": 0
      },
      {
        "bucket_start": "2026-07-24T13:41:25.714287+00:00",
        "bucket_end": "2026-07-24T13:45:42.857144+00:00",
        "positive": 0,
        "neutral": 0,
        "negative": 0
      },
      {
        "bucket_start": "2026-07-24T13:45:42.857144+00:00",
        "bucket_end": "2026-07-24T13:50:00.000001+00:00",
        "positive": 0,
        "neutral": 0,
        "negative": 0
      },
      {
        "bucket_start": "2026-07-24T13:50:00.000001+00:00",
        "bucket_end": "2026-07-24T13:54:17.142858+00:00",
        "positive": 0,
        "neutral": 0,
        "negative": 0
      },
      {
        "bucket_start": "2026-07-24T13:54:17.142858+00:00",
        "bucket_end": "2026-07-24T13:58:34.285715+00:00",
        "positive": 0,
        "neutral": 0,
        "negative": 0
      },
      {
        "bucket_start": "2026-07-24T13:58:34.285715+00:00",
        "bucket_end": "2026-07-24T14:02:51.428572+00:00",
        "positive": 1,
        "neutral": 0,
        "negative": 1
      },
      {
        "bucket_start": "2026-07-24T14:02:51.428572+00:00",
        "bucket_end": "2026-07-24T14:07:08.571429+00:00",
        "positive": 1,
        "neutral": 1,
        "negative": 1
      },
      {
        "bucket_start": "2026-07-24T14:07:08.571429+00:00",
        "bucket_end": "2026-07-24T14:11:25.714286+00:00",
        "positive": 0,
        "neutral": 0,
        "negative": 0
      },
      {
        "bucket_start": "2026-07-24T14:11:25.714286+00:00",
        "bucket_end": "2026-07-24T14:15:42.857143+00:00",
        "positive": 1,
        "neutral": 0,
        "negative": 0
      },
      {
        "bucket_start": "2026-07-24T14:15:42.857143+00:00",
        "bucket_end": "2026-07-24T14:20:00+00:00",
        "positive": 1,
        "neutral": 0,
        "negative": 1
      }
    ],
    "coverage_focus_ranking": [
      {
        "handle": "yutinghaosfinance",
        "top_topic_id": 0,
        "top_topic_label": "全年需求可能寫下 / 逐步轉型為人工智慧與科技產業重鎮 / 紐約正從傳統金融中心 / 若下半年維持相同速度",
        "focus_share": 1.0,
        "post_count": 9
      }
    ],
    "top_engagement_ranking": [
      {
        "topic_id": 0,
        "label": "全年需求可能寫下 / 逐步轉型為人工智慧與科技產業重鎮 / 紐約正從傳統金融中心 / 若下半年維持相同速度",
        "total_engagement": 890,
        "post_count": 9
      }
    ],
    "posting_timeslot_analysis": {
      "slots": {
        "morning": {
          "post_count": 0,
          "likes": 0,
          "engagement": 0,
          "avg_engagement": 0.0
        },
        "afternoon": {
          "post_count": 0,
          "likes": 0,
          "engagement": 0,
          "avg_engagement": 0.0
        },
        "evening": {
          "post_count": 9,
          "likes": 890,
          "engagement": 890,
          "avg_engagement": 98.9
        },
        "late_night": {
          "post_count": 0,
          "likes": 0,
          "engagement": 0,
          "avg_engagement": 0.0
        }
      },
      "peak_slot": "evening"
    },
    "competitor_mentions": null,
    "platform_share_bar": null,
    "platform_keyword_ranking": null
  },
  "note": "competitor_mentions/platform_share_bar/platform_keyword_ranking require a keyword argument"
}