{
  "generated_at": "2026-07-24T10:16:29.717000+08:00",
  "time_range": "1d",
  "window": {
    "start_utc": "2026-07-23T10:16:29.717000+08:00",
    "end_utc": "2026-07-24T10:16:29.717000+08:00",
    "start_tw": "Jul 23, 10:16",
    "end_tw": "Jul 24, 10:16"
  },
  "keyword": null,
  "widgets": {
    "sentiment_overview": {
      "total_posts": 184,
      "sentiment_counts": {
        "positive": 100,
        "neutral": 52,
        "negative": 32
      },
      "sentiment_share": {
        "positive": 0.543,
        "neutral": 0.283,
        "negative": 0.174
      },
      "top_terms": [
        "photonics",
        "optica",
        "optical",
        "infrastructure",
        "manufacturing",
        "photonic",
        "scale",
        "volume",
        "optics",
        "ceo"
      ]
    },
    "temperature_bar": [
      {
        "topic_id": 1,
        "label": "ai / photonics / hashtag / optical",
        "heat": 90.0,
        "volume": 132,
        "engagement": 9983,
        "entities": [
          "AI",
          "XIVER",
          "PhotonPath",
          "Taiwan",
          "Quantum"
        ]
      },
      {
        "topic_id": 13,
        "label": "intel / 英特爾 / cpu / amd",
        "heat": 12.2,
        "volume": 6,
        "engagement": 458,
        "entities": [
          "Intel",
          "中國",
          "intel",
          "英特爾",
          "伺服器"
        ]
      },
      {
        "topic_id": 16,
        "label": "nvidia / gpus / guarantee / semianalysis",
        "heat": 11.2,
        "volume": 4,
        "engagement": 1136,
        "entities": [
          "gpu",
          "Chinese",
          "Nvidia    V HVDC",
          "AI",
          "Nvidia"
        ]
      },
      {
        "topic_id": 12,
        "label": "quantum / shelf / qkd / fibre",
        "heat": 10.6,
        "volume": 3,
        "engagement": 225,
        "entities": [
          "QUANTUM",
          "Glasgow",
          "Optica Quantum     ",
          "the Quantum Industry Summit",
          "Scottish"
        ]
      },
      {
        "topic_id": 5,
        "label": "ttm / stg / aerospace / implantable",
        "heat": 10.6,
        "volume": 3,
        "engagement": 126,
        "entities": [
          "TTM",
          "STG",
          "European",
          "TTM Technologies",
          "PCB"
        ]
      },
      {
        "topic_id": 8,
        "label": "quantum / bn / glasgow / usd",
        "heat": 10.6,
        "volume": 3,
        "engagement": 159,
        "entities": [
          "Quantum",
          "USD",
          "GBP",
          "QUANTUM SCALE OR",
          "the Optica Quantum     "
        ]
      },
      {
        "topic_id": 3,
        "label": "lutz / fusion / photonics / costs",
        "heat": 10.6,
        "volume": 3,
        "engagement": 225,
        "entities": [
          "Lutz",
          "Europe",
          "Photonics",
          "Light Conversion",
          "Lithuania"
        ]
      },
      {
        "topic_id": 4,
        "label": "inp / direct / inch / nvidia",
        "heat": 10.4,
        "volume": 3,
        "engagement": 54,
        "entities": [
          "InP",
          "European",
          "NYSE",
          "COHR",
          "the U S  Department of Commerce"
        ]
      },
      {
        "topic_id": 11,
        "label": "runs / ai / ceo / manufacturing",
        "heat": 10.4,
        "volume": 3,
        "engagement": 54,
        "entities": [
          "AI",
          "Sherman",
          "Texas",
          "Jensen Huang",
          "Coherent Corp"
        ]
      },
      {
        "topic_id": 9,
        "label": "rack / blackwell / vera / rubin",
        "heat": 10.3,
        "volume": 3,
        "engagement": 32,
        "entities": [
          "HBM",
          "Blackwell",
          "Vera Rubin"
        ]
      },
      {
        "topic_id": 6,
        "label": "ai / mission",
        "heat": 10.1,
        "volume": 5,
        "engagement": 13,
        "entities": [
          "季增",
          "馬斯克",
          "奧德賽",
          "緯創",
          "韓國"
        ]
      },
      {
        "topic_id": 7,
        "label": "rubin / software / gb / vs",
        "heat": 10.0,
        "volume": 2,
        "engagement": 234,
        "entities": [
          "輝達",
          "嚴正",
          "Rubin NVL   ",
          "GB    NVL     Inference TCO   Architecture Analysis",
          "Rubin LUT Based"
        ]
      },
      {
        "topic_id": 17,
        "label": "hynix / sk / billion / revenue",
        "heat": 10.0,
        "volume": 2,
        "engagement": 200,
        "entities": [
          "Morgan Stanley",
          "U S",
          "morgan stanley",
          "SK Hynix"
        ]
      },
      {
        "topic_id": 0,
        "label": "fcc / link",
        "heat": 10.0,
        "volume": 2,
        "engagement": 106,
        "entities": [
          "台灣",
          "國安",
          "友訊",
          "美國",
          "中國"
        ]
      },
      {
        "topic_id": 14,
        "label": "summary / excellent",
        "heat": 10.0,
        "volume": 3,
        "engagement": 0,
        "entities": [
          "Worth"
        ]
      },
      {
        "topic_id": 2,
        "label": "quantum / glasgow / hardware / jose",
        "heat": 10.0,
        "volume": 3,
        "engagement": 0,
        "entities": [
          "UK",
          "Glasgow",
          "Scotland",
          "Optica s Quantum     Conference",
          "Jose Pozo  CTO"
        ]
      },
      {
        "topic_id": 10,
        "label": "asml / niesing / lithography / photonics",
        "heat": 10.0,
        "volume": 2,
        "engagement": 88,
        "entities": [
          "Niesing",
          "PHOTONICS",
          "the Optica GAMA Meeting      ",
          "Brussels",
          "Henk Niesing"
        ]
      },
      {
        "topic_id": 15,
        "label": "equipment / ip / scale / manufacturing",
        "heat": 10.0,
        "volume": 2,
        "engagement": 74,
        "entities": [
          "European",
          "Brussels",
          "Europe",
          "China",
          "Optica GAMA"
        ]
      }
    ],
    "named_entities": [
      {
        "entity": "AI",
        "count": 43
      },
      {
        "entity": "European",
        "count": 29
      },
      {
        "entity": "Europe",
        "count": 20
      },
      {
        "entity": "Quantum",
        "count": 15
      },
      {
        "entity": "XIVER",
        "count": 15
      },
      {
        "entity": "TTM",
        "count": 15
      },
      {
        "entity": "Brussels",
        "count": 15
      },
      {
        "entity": "US",
        "count": 14
      },
      {
        "entity": "Optica",
        "count": 14
      },
      {
        "entity": "Intel",
        "count": 13
      },
      {
        "entity": "UK",
        "count": 13
      },
      {
        "entity": "Glasgow",
        "count": 12
      },
      {
        "entity": "PhotonPath",
        "count": 12
      },
      {
        "entity": "STG",
        "count": 12
      },
      {
        "entity": "中國",
        "count": 11
      }
    ],
    "sentiment_trend_curve": [
      {
        "bucket_start": "2026-07-23T10:16:29.717006+08:00",
        "bucket_end": "2026-07-23T11:59:21.145577+08:00",
        "positive": 11,
        "neutral": 8,
        "negative": 4
      },
      {
        "bucket_start": "2026-07-23T11:59:21.145577+08:00",
        "bucket_end": "2026-07-23T13:42:12.574148+08:00",
        "positive": 6,
        "neutral": 11,
        "negative": 1
      },
      {
        "bucket_start": "2026-07-23T13:42:12.574148+08:00",
        "bucket_end": "2026-07-23T15:25:04.002719+08:00",
        "positive": 5,
        "neutral": 12,
        "negative": 4
      },
      {
        "bucket_start": "2026-07-23T15:25:04.002719+08:00",
        "bucket_end": "2026-07-23T17:07:55.431290+08:00",
        "positive": 10,
        "neutral": 5,
        "negative": 1
      },
      {
        "bucket_start": "2026-07-23T17:07:55.431290+08:00",
        "bucket_end": "2026-07-23T18:50:46.859861+08:00",
        "positive": 29,
        "neutral": 1,
        "negative": 7
      },
      {
        "bucket_start": "2026-07-23T18:50:46.859861+08:00",
        "bucket_end": "2026-07-23T20:33:38.288432+08:00",
        "positive": 4,
        "neutral": 2,
        "negative": 0
      },
      {
        "bucket_start": "2026-07-23T20:33:38.288432+08:00",
        "bucket_end": "2026-07-23T22:16:29.717003+08:00",
        "positive": 3,
        "neutral": 4,
        "negative": 3
      },
      {
        "bucket_start": "2026-07-23T22:16:29.717003+08:00",
        "bucket_end": "2026-07-23T23:59:21.145574+08:00",
        "positive": 13,
        "neutral": 0,
        "negative": 2
      },
      {
        "bucket_start": "2026-07-23T23:59:21.145574+08:00",
        "bucket_end": "2026-07-24T01:42:12.574145+08:00",
        "positive": 2,
        "neutral": 2,
        "negative": 2
      },
      {
        "bucket_start": "2026-07-24T01:42:12.574145+08:00",
        "bucket_end": "2026-07-24T03:25:04.002716+08:00",
        "positive": 2,
        "neutral": 0,
        "negative": 1
      },
      {
        "bucket_start": "2026-07-24T03:25:04.002716+08:00",
        "bucket_end": "2026-07-24T05:07:55.431287+08:00",
        "positive": 1,
        "neutral": 2,
        "negative": 2
      },
      {
        "bucket_start": "2026-07-24T05:07:55.431287+08:00",
        "bucket_end": "2026-07-24T06:50:46.859858+08:00",
        "positive": 1,
        "neutral": 2,
        "negative": 2
      },
      {
        "bucket_start": "2026-07-24T06:50:46.859858+08:00",
        "bucket_end": "2026-07-24T08:33:38.288429+08:00",
        "positive": 3,
        "neutral": 2,
        "negative": 1
      },
      {
        "bucket_start": "2026-07-24T08:33:38.288429+08:00",
        "bucket_end": "2026-07-24T10:16:29.717000+08:00",
        "positive": 4,
        "neutral": 1,
        "negative": 1
      }
    ],
    "coverage_focus_ranking": [
      {
        "handle": "tphuang",
        "top_topic_id": 1,
        "top_topic_label": "ai / photonics / hashtag / optical",
        "focus_share": 1.0,
        "post_count": 11
      },
      {
        "handle": "tengyanAI",
        "top_topic_id": 1,
        "top_topic_label": "ai / photonics / hashtag / optical",
        "focus_share": 1.0,
        "post_count": 10
      },
      {
        "handle": "FT",
        "top_topic_id": 1,
        "top_topic_label": "ai / photonics / hashtag / optical",
        "focus_share": 1.0,
        "post_count": 1
      },
      {
        "handle": "ctee.fans",
        "top_topic_id": 1,
        "top_topic_label": "ai / photonics / hashtag / optical",
        "focus_share": 0.95,
        "post_count": 20
      },
      {
        "handle": "technewsinside",
        "top_topic_id": 1,
        "top_topic_label": "ai / photonics / hashtag / optical",
        "focus_share": 0.8,
        "post_count": 30
      },
      {
        "handle": "TrendForce",
        "top_topic_id": 1,
        "top_topic_label": "ai / photonics / hashtag / optical",
        "focus_share": 0.75,
        "post_count": 4
      },
      {
        "handle": "subhash-km-6b5443123",
        "top_topic_id": 1,
        "top_topic_label": "ai / photonics / hashtag / optical",
        "focus_share": 0.75,
        "post_count": 16
      },
      {
        "handle": "jukan05",
        "top_topic_id": 1,
        "top_topic_label": "ai / photonics / hashtag / optical",
        "focus_share": 0.667,
        "post_count": 12
      },
      {
        "handle": "SemiAnalysis_",
        "top_topic_id": 1,
        "top_topic_label": "ai / photonics / hashtag / optical",
        "focus_share": 0.6,
        "post_count": 10
      },
      {
        "handle": "QQ_Timmy",
        "top_topic_id": 1,
        "top_topic_label": "ai / photonics / hashtag / optical",
        "focus_share": 0.556,
        "post_count": 9
      },
      {
        "handle": "josepozophotonics",
        "top_topic_id": 1,
        "top_topic_label": "ai / photonics / hashtag / optical",
        "focus_share": 0.541,
        "post_count": 61
      }
    ],
    "top_engagement_ranking": [
      {
        "topic_id": 1,
        "label": "ai / photonics / hashtag / optical",
        "total_engagement": 9983,
        "post_count": 132
      },
      {
        "topic_id": 16,
        "label": "nvidia / gpus / guarantee / semianalysis",
        "total_engagement": 1136,
        "post_count": 4
      },
      {
        "topic_id": 13,
        "label": "intel / 英特爾 / cpu / amd",
        "total_engagement": 458,
        "post_count": 6
      },
      {
        "topic_id": 7,
        "label": "rubin / software / gb / vs",
        "total_engagement": 234,
        "post_count": 2
      },
      {
        "topic_id": 12,
        "label": "quantum / shelf / qkd / fibre",
        "total_engagement": 225,
        "post_count": 3
      },
      {
        "topic_id": 3,
        "label": "lutz / fusion / photonics / costs",
        "total_engagement": 225,
        "post_count": 3
      },
      {
        "topic_id": 17,
        "label": "hynix / sk / billion / revenue",
        "total_engagement": 200,
        "post_count": 2
      },
      {
        "topic_id": 8,
        "label": "quantum / bn / glasgow / usd",
        "total_engagement": 159,
        "post_count": 3
      },
      {
        "topic_id": 5,
        "label": "ttm / stg / aerospace / implantable",
        "total_engagement": 126,
        "post_count": 3
      },
      {
        "topic_id": 0,
        "label": "fcc / link",
        "total_engagement": 106,
        "post_count": 2
      },
      {
        "topic_id": 10,
        "label": "asml / niesing / lithography / photonics",
        "total_engagement": 88,
        "post_count": 2
      },
      {
        "topic_id": 15,
        "label": "equipment / ip / scale / manufacturing",
        "total_engagement": 74,
        "post_count": 2
      },
      {
        "topic_id": 4,
        "label": "inp / direct / inch / nvidia",
        "total_engagement": 54,
        "post_count": 3
      },
      {
        "topic_id": 11,
        "label": "runs / ai / ceo / manufacturing",
        "total_engagement": 54,
        "post_count": 3
      },
      {
        "topic_id": 9,
        "label": "rack / blackwell / vera / rubin",
        "total_engagement": 32,
        "post_count": 3
      },
      {
        "topic_id": 6,
        "label": "ai / mission",
        "total_engagement": 13,
        "post_count": 5
      },
      {
        "topic_id": 14,
        "label": "summary / excellent",
        "total_engagement": 0,
        "post_count": 3
      },
      {
        "topic_id": 2,
        "label": "quantum / glasgow / hardware / jose",
        "total_engagement": 0,
        "post_count": 3
      }
    ],
    "posting_timeslot_analysis": {
      "slots": {
        "morning": {
          "post_count": 46,
          "likes": 2227,
          "engagement": 2514,
          "avg_engagement": 54.7
        },
        "afternoon": {
          "post_count": 89,
          "likes": 6743,
          "engagement": 7558,
          "avg_engagement": 84.9
        },
        "evening": {
          "post_count": 34,
          "likes": 2059,
          "engagement": 2320,
          "avg_engagement": 68.2
        },
        "late_night": {
          "post_count": 15,
          "likes": 669,
          "engagement": 775,
          "avg_engagement": 51.7
        }
      },
      "peak_slot": "afternoon"
    },
    "competitor_mentions": null,
    "platform_share_bar": null,
    "platform_keyword_ranking": null
  },
  "note": "competitor_mentions/platform_share_bar/platform_keyword_ranking require a keyword argument"
}